upseeker/__init__.py
upseeker/upseeker.cpython-310-linux.so
upseeker/upseeker.cpython-311-linux.so
upseeker/upseeker.cpython-312-linux.so
upseeker/upseeker.cpython-313-linux.so
upseeker/upseeker.cpython-38-linux.so
upseeker/upseeker.cpython-39-linux.so
upseeker/upseeker.py
upseeker/bin/coll-linux
upseeker/scripts/seekeragg.sh
upseeker-0.0.7.dist-info/._top_level.txt
upseeker-0.0.7.dist-info/AUTHORS.rst
upseeker-0.0.7.dist-info/LICENSE.rst
upseeker-0.0.7.dist-info/METADATA
upseeker-0.0.7.dist-info/WHEEL
upseeker-0.0.7.dist-info/top_level.txt
upseeker-0.0.7.dist-info/RECORD
